{
  "version": 1,
  "serviceConfiguration": {
    "apiName": "guitartaborganizer",
    "serviceName": "AppSync",
    "gqlSchemaPath": "/tmp/amplify-d1effcc9-1551-4dff-a52d-7d74068fcdba/amplify/backend/api/guitartaborganizer/schema.graphql",
    "defaultAuthType": {
      "mode": "API_KEY",
      "keyDescription": "api key description",
      "expirationTime": 30
    },
    "additionalAuthTypes": [
      {
        "mode": "AWS_IAM"
      },
      {
        "mode": "AMAZON_COGNITO_USER_POOLS",
        "cognitoUserPoolId": "authguitartaborganizerfa2a470e"
      }
    ],
    "conflictResolution": {
      "defaultResolutionStrategy": {
        "type": "AUTOMERGE"
      }
    }
  }
}